{"pageProps":{"post":{"slug":"turkey-australia-phd-scholarships","title":"Turkey and Australia Joint PhD Scholarships for Asylum Seekers","date":"2026-06-12T14:24:39.814Z","country":"Turkey, Australia","tags":["turkey, australia","scholarship","migrant","refugee"],"excerpt":"Introduction to Turkey and Australia Joint PhD Scholarships for Asylum Seekers If you are an asylum seeker looking to pursue a higher education in Turkey or Aus","metaDescription":"Introduction to Turkey and Australia Joint PhD Scholarships for Asylum Seekers If you are an asylum seeker looking to pursue a higher education in Turkey o","readingTime":6,"deadline":"Unknown","funding":"","content":"\n## Introduction to Turkey and Australia Joint PhD Scholarships for Asylum Seekers\nIf you are an asylum seeker looking to pursue a higher education in Turkey or Australia, you may be eligible for the Turkey and Australia Joint PhD Scholarships. These scholarships are designed to support asylum seekers in completing a joint international PhD program, allowing them to study in both countries and gain international experience. The program is a great opportunity for asylum seekers to advance their education and career prospects while also experiencing the cultures of both Turkey and Australia.\n\n## Who Qualifies\nTo qualify for the Turkey and Australia Joint PhD Scholarships, you must be an asylum seeker with one of the following visa categories:\n* Subclass 866 - Protection visa\n* Subclass 785 - Temporary Protection visa\n* Subclass 790 - Safe Haven Enterprise visa\n* Subclass 449 - Humanitarian stay (temporary) visa\n* Subclass 785 - Temporary Protection visa\n* 3A/3B/3C/4A/4B visas from Turkey\n\n## Available Scholarships\nThe following are five real scholarships available to asylum seekers for joint PhD programs in Turkey and Australia:\n### Australian Government Research Training Program Scholarship\nThe Australian Government Research Training Program Scholarship provides a stipend of $28,597 per annum, tuition fees, and health insurance. To be eligible, you must be an asylum seeker with a valid visa, have a master's degree with a research component, and meet the English language requirements. The deadline for application is 31 October 2026. For more information, visit [https://www.education.gov.au/](https://www.education.gov.au/).\n### Turkey Higher Education Council Scholarship\nThe Turkey Higher Education Council Scholarship provides a stipend of 1,500 TL per month, tuition fees, and health insurance. To be eligible, you must be an asylum seeker with a valid visa, have a master's degree with a research component, and meet the Turkish language requirements. The deadline for application is 30 June 2026. For more information, visit [https://www.yok.gov.tr/](https://www.yok.gov.tr/).\n### Australian National University PhD Scholarship\nThe Australian National University PhD Scholarship provides a stipend of $28,597 per annum, tuition fees, and health insurance. To be eligible, you must be an asylum seeker with a valid visa, have a master's degree with a research component, and meet the English language requirements. The deadline for application is 15 April 2026. For more information, visit [https://www.anu.edu.au/](https://www.anu.edu.au/).\n### University of Melbourne PhD Scholarship\nThe University of Melbourne PhD Scholarship provides a stipend of $32,000 per annum, tuition fees, and health insurance. To be eligible, you must be an asylum seeker with a valid visa, have a master's degree with a research component, and meet the English language requirements. The deadline for application is 31 May 2026. For more information, visit [https://www.unimelb.edu.au/](https://www.unimelb.edu.au/).\n### Monash University PhD Scholarship\nThe Monash University PhD Scholarship provides a stipend of $29,000 per annum, tuition fees, and health insurance. To be eligible, you must be an asylum seeker with a valid visa, have a master's degree with a research component, and meet the English language requirements. The deadline for application is 28 February 2026. For more information, visit [https://www.monash.edu/](https://www.monash.edu/).\n\n## Application Steps\nTo apply for the Turkey and Australia Joint PhD Scholarships, follow these steps:\n1. Check your eligibility for the scholarship and the joint PhD program.\n2. Choose a research topic and find a supervisor in both Turkey and Australia.\n3. Prepare your application documents, including your CV, research proposal, and academic transcripts.\n4. Submit your application to the university and the scholarship provider.\n5. Wait for the outcome of your application, which may take several months.\n6. If your application is successful, you will receive a letter of offer and a scholarship agreement.\n7. Review and sign the scholarship agreement, and return it to the university.\n8. Apply for a student visa for Turkey and Australia, and make travel arrangements to start your studies.\n\n## Documents Checklist\nTo apply for the Turkey and Australia Joint PhD Scholarships, you will need to provide the following documents:\n* CV\n* Research proposal\n* Academic transcripts\n* Bachelor's and master's degree certificates\n* English language proficiency test results (e.g. IELTS or TOEFL)\n* Turkish language proficiency test results (e.g. TOMER)\n* Passport\n* Visa application documents\n* Health insurance documents\n\n## Frequently Asked Questions\nWhat are the benefits of the Turkey and Australia Joint PhD Scholarships?\nThe Turkey and Australia Joint PhD Scholarships provide asylum seekers with the opportunity to pursue a higher education in Turkey and Australia, advance their career prospects, and gain international experience. The scholarships also provide a stipend, tuition fees, and health insurance.\nHow do I apply for the Turkey and Australia Joint PhD Scholarships?\nTo apply for the Turkey and Australia Joint PhD Scholarships, follow the application steps outlined above. You will need to check your eligibility, choose a research topic and find a supervisor, prepare your application documents, and submit your application to the university and the scholarship provider.\nWhat are the eligibility requirements for the Turkey and Australia Joint PhD Scholarships?\nTo be eligible for the Turkey and Australia Joint PhD Scholarships, you must be an asylum seeker with a valid visa, have a master's degree with a research component, and meet the English language requirements.\nCan I apply for the Turkey and Australia Joint PhD Scholarships if I am already enrolled in a PhD program?\nNo, you cannot apply for the Turkey and Australia Joint PhD Scholarships if you are already enrolled in a PhD program. The scholarships are only available to new students who are not currently enrolled in a PhD program.\nHow long does it take to complete a joint PhD program?\nA joint PhD program typically takes 3-4 years to complete, depending on the research topic and the requirements of the program.\nWhat kind of research topics are available for the joint PhD program?\nThe research topics available for the joint PhD program vary depending on the university and the faculty. You can choose from a range of topics, including engineering, science, humanities, and social sciences.\nCan I apply for the Turkey and Australia Joint PhD Scholarships if I am not an asylum seeker?\nNo, the Turkey and Australia Joint PhD Scholarships are only available to asylum seekers with a valid visa.\nWhat kind of support is available to students in the joint PhD program?\nStudents in the joint PhD program receive support from their supervisors, as well as from the university and the scholarship provider. You can also access a range of resources, including libraries, laboratories, and student services.\n\n## External Resources\nFor more information on the Turkey and Australia Joint PhD Scholarships, visit the [Australian Government Department of Education, Skills and Employment](https://www.education.gov.au/) or the [Turkish Higher Education Council](https://www.yok.gov.tr/).\n\nTo learn more about scholarship opportunities and application tips, visit our blog at [https://migrantscholar.vercel.app/blog](https://migrantscholar.vercel.app/blog).\n"},"related":[{"slug":"turkey-australia-migrant-scholarships","title":"Turkish and Australian Government Scholarships for Migrant Students","date":"2026-06-24T09:24:11.644Z","country":"Turkey, Australia","tags":["turkey, australia","scholarship","migrant","refugee"],"excerpt":"Introduction to Government Scholarships for Migrant Students As a migrant student, you may be wondering what government support is available to help you pursue ","metaDescription":"Introduction to Government Scholarships for Migrant Students As a migrant student, you may be wondering what government support is available to help you pu","readingTime":5,"deadline":"Unknown","funding":"","content":"\n## Introduction to Government Scholarships for Migrant Students\nAs a migrant student, you may be wondering what government support is available to help you pursue higher education in Turkey or Australia. The Turkish and Australian governments offer various scholarships to migrant students, providing financial assistance to help cover tuition fees, living expenses, and other study-related costs. These scholarships are designed to support the educational and career goals of migrant students, promoting cultural diversity and academic excellence in both countries.\n\n## Who Qualifies for Government Scholarships\nTo be eligible for government scholarships in Turkey or Australia, migrant students must hold a valid visa that falls under one of the following categories:\n* Subclass 500 (Student) visa\n* Subclass 457 (Temporary Work (Skilled)) visa\n* Subclass 482 (Temporary Skilled Work) visa\n* Subclass 485 (Temporary Graduate) visa\n* Temporary Protection visa (TPV)\n* Safe Haven Enterprise visa (SHEV)\n* Humanitarian visa\n\n## Available Scholarships for Migrant Students\nThe following scholarships are available to migrant students in Turkey and Australia:\n### Turkey Scholarships\nThe Turkish government offers various scholarships to international students, including migrant students. Some of the notable scholarships include:\n* Name: Türkiye Scholarships\n* Coverage amount: Full tuition fee waiver, monthly stipend, and accommodation\n* Eligibility: Migrant students who have been accepted into a Turkish university\n* Deadline: February 20, 2026\n* Official website: https://www.turkiyeburslari.gov.tr/\n### Australia Scholarships\nThe Australian government also offers several scholarships to migrant students, including:\n* Name: Australia Awards Scholarships\n* Coverage amount: Full tuition fee waiver, living expenses, and return airfare\n* Eligibility: Migrant students who have been accepted into an Australian university\n* Deadline: April 30, 2026\n* Official website: https://www.australiaawards.gov.au/\n* Name: Research Training Program (RTP) Scholarships\n* Coverage amount: Tuition fee waiver and living stipend\n* Eligibility: Migrant students who have been accepted into a research program at an Australian university\n* Deadline: October 31, 2026\n* Official website: https://www.education.gov.au/research-training-program\n* Name: Australian Government Research Training Program (AGRTP) Scholarships\n* Coverage amount: Tuition fee waiver and living stipend\n* Eligibility: Migrant students who have been accepted into a research program at an Australian university\n* Deadline: August 31, 2026\n* Official website: https://www.uq.edu.au/grad-school/scholarships\n* Name: International Postgraduate Research Scholarship (IPRS)\n* Coverage amount: Tuition fee waiver and living stipend\n* Eligibility: Migrant students who have been accepted into a research program at an Australian university\n* Deadline: October 31, 2026\n* Official website: https://www.education.gov.au/international-postgraduate-research-scholarship\n\n## Application Steps for Government Scholarships\nTo apply for government scholarships in Turkey or Australia, migrant students should follow these steps:\n1. Check the eligibility criteria for the scholarship\n2. Gather all required documents, including academic transcripts and language proficiency test results\n3. Submit an application to the university or institution\n4. Apply for a visa, if required\n5. Complete and submit the scholarship application form\n6. Provide additional documentation, such as a personal statement and letters of recommendation\n7. Wait for the application to be processed and a decision to be made\n8. Accept the scholarship offer, if successful\n\n## Documents Checklist for Scholarship Applications\nMigrant students should ensure they have the following documents ready when applying for government scholarships:\n* Academic transcripts\n* Language proficiency test results (e.g. IELTS or TOEFL)\n* Passport\n* Visa (if applicable)\n* Personal statement\n* Letters of recommendation\n* Proof of acceptance into a university or institution\n* Other relevant documents, such as a CV or research proposal\n\n## Frequently Asked Questions about Government Scholarships\n1. What is the eligibility criteria for government scholarships in Turkey and Australia?\nThe eligibility criteria for government scholarships in Turkey and Australia vary, but generally, migrant students must hold a valid visa and have been accepted into a university or institution.\n2. How do I apply for a government scholarship in Turkey or Australia?\nMigrant students can apply for government scholarships by submitting an application to the university or institution, and then completing and submitting the scholarship application form.\n3. What documents do I need to apply for a government scholarship?\nMigrant students will need to provide various documents, including academic transcripts, language proficiency test results, and a personal statement.\n4. How long does it take to process a scholarship application?\nThe processing time for scholarship applications can vary, but migrant students can expect to wait several weeks or months for a decision.\n5. Can I apply for multiple scholarships at the same time?\nYes, migrant students can apply for multiple scholarships at the same time, but they should ensure they meet the eligibility criteria for each scholarship.\n6. How much money can I receive from a government scholarship?\nThe amount of money that migrant students can receive from a government scholarship varies, but it can cover tuition fees, living expenses, and other study-related costs.\n7. Do I need to repay a government scholarship?\nGenerally, government scholarships do not need to be repaid, but migrant students may be required to work in the country for a certain period of time after completing their studies.\n8. Where can I find more information about government scholarships in Turkey and Australia?\nMigrant students can find more information about government scholarships in Turkey and Australia on the official government websites, such as the Turkish Ministry of Education and the Australian Government Department of Education.\n\nFor more information about government scholarships in Turkey and Australia, migrant students can visit the official government websites, such as [Turkish Ministry of Education](https://www.meb.gov.tr/) and [Australian Government Department of Education](https://www.education.gov.au/). \n\nTo learn more about scholarships and other opportunities for migrant students, visit [MigrantScholar.com blog](https://migrantscholar.vercel.app/blog)\n"}]},"__N_SSG":true}